{
  "offset": 0,
  "numFound": 7,
  "resultTypesAvailable": [
    "DIRECT_MATCH"
  ],
  "errors": [],
  "flattenedQuery": null,
  "results": [
    {
      "numFound": 7,
      "offset": 0,
      "metaData": {
        "lowestPrice": 32.99,
        "highestDiscount": 0,
        "resultType": "DIRECT_MATCH",
        "uniqueFacetValuesPerFacet": []
      },
      "stats": [],
      "categorySet": [],
      "errors": [],
      "flattenedQuery": "",
      "categoryDirectionMarkers": [],
      "resultSet": [
        {
          "id": "3G6ftwpEqsKLu2V8REoGDhhEBcAQ",
          "type": "nonmatching",
          "productSearchId": {
            "familyIdV3": "3G6ftwpEqsKLu2V8REoGDhhEBcAQ",
            "advertisementIdV3": "3G6ftwpEqsKLu2V8REoGDhhEBcAQ"
          },
          "shopItemId": 968952457,
          "productId": "3G6ftwpEqsKLu2V8REoGDhhEBcAQ",
          "ean": "",
          "shopInfo": {
            "id": 16034,
            "shopName": "Drogist.nl",
            "shopPhase": 1,
            "isActive": true,
            "isAffiliate": false,
            "hasFreeReturnCondition": false,
            "shopType": "CPC",
            "isClosedOnSunday": false,
            "isBlendedCpcWw": false,
            "isCSSShop": false,
            "allowBackOrder": true,
            "sortLower": null,
            "feedBiddingEnabled": false,
            "smartBiddingEnabled": true,
            "listedOnNl": true,
            "listedOnBe": true,
            "bvBucket": 3,
            "productCount": 75046,
            "isDisabled": false,
            "hideOnline": false,
            "includesVat": true,
            "logo": "/beslist-images/shop_images/LARGE/16034.png",
            "coolingOffPeriod": 14,
            "activeSince": "2025-04-15T05:02:26+02:00",
            "emailGeneral": "",
            "emailFinanceAdmin": "",
            "emailCustomerContact": "info@Drogist.nl",
            "sharesGoogleAnalyticsData": false,
            "principalClient": {
              "clientId": 2016,
              "clientName": "",
              "clientAddress": "",
              "clientZipCode": "",
              "clientCity": "",
              "clientCountry": "",
              "clientEmailITAccess": "",
              "clientEmailGeneral": "",
              "clientEmailFinanceAdmin": "",
              "clientEmailCustomerContact": "",
              "clientVatNumber": ""
            },
            "deliveryCompanies": [
              {
                "id": 4,
                "name": "DHL"
              }
            ],
            "paymentOptions": [
              {
                "id": 17,
                "name": "iDEAL"
              },
              {
                "id": 9,
                "name": "PayPal"
              },
              {
                "id": 18,
                "name": "Visa"
              },
              {
                "id": 19,
                "name": "Mastercard"
              },
              {
                "id": 35,
                "name": "Maestro"
              },
              {
                "id": 24,
                "name": "Bancontact"
              }
            ],
            "qualityMarks": [
              {
                "id": 2,
                "name": "Thuiswinkel Waarborg"
              }
            ]
          },
          "shopItem": {
            "shopId": 16034,
            "shopItemId": 968952457,
            "shopItemTitle": "Voltaren Emulgel extra sterk 2,32% (diclofenac)  bij spier- of gewrichtspijn 150 Gram",
            "shopItemDescription": "",
            "shopItemVersion": "144238",
            "shopName": "Drogist.nl",
            "shopType": "CPC",
            "productIdentifier": "",
            "productIdV3": "3G6ftwpEqsKLu2V8REoGDhhEBcAQ",
            "condition": "Nieuw",
            "ean": "5054563923912",
            "blockStatus": 0,
            "disabledInFeed": false,
            "url": "https://www.drogist.nl/voltaren-emulgel-extra-sterk-232-diclofenac-bij-spier-of-gewrichtspijn-150-gram.htm?channable=004ab8696400313434323338e2&utm_campaign=feed&utm_content=Gezondheid%20%3E%20Geneesmiddelen%20%3E%20Pijn%20%3E%20Algemene%20Pijnstillers%20%3E%20Diclofenac%20Voltaren&utm_source=beslist&utm_medium=cpc&utm_term=144238",
            "size": "",
            "shopReviewScore": 9.4,
            "shopReviewAmount": 85784,
            "isBlendedCpcWw": false,
            "shopPhase": 1,
            "salePrice": null,
            "regularPrice": {
              "bucket": 21,
              "price": 32.99,
              "validFrom": null,
              "validThrough": null
            },
            "bvbCode": "144238",
            "bidLabel": null
          },
          "pim": {
            "groupId": null,
            "title": "Voltaren Emulgel Extra Sterk 2,32% - 1 x 150 gr",
            "description": "Voltaren Emulgel Voltaren Emulgel Extra Sterk 2,32% is een ontstekingsremmende gel die wordt gebruikt voor de lokale verlichting van milde tot matige gewrichtspijn, zoals veroorzaakt door artrose, in de knie\u00ebn en vingers. Voltaren Emulgel Extra Sterk bevat een extra sterke concentratie (2,32%) diclofenac, een niet-stero\u00efdale ontstekingsremmer (NSAID). Diclofenac werkt pijnstillend en ontstekingsremmend in de bron. De pijnverlichting van Voltaren Emulgel bouwt zich geleidelijk op gedurende de eerste week van de behandeling. 1 keer aanbrengen per 12 uur op de te behandelen plek. Voltaren Emulgel Extra Sterk 2,32% nu met een nieuwe makkelijk te openen dop in 1 klik. Voltaren Emulgel 2,32% (diclofenac diethylammononium) is een geneesmiddel. Voltaren niet gebruiken gedurende het laatste trimester van de zwangerschap.",
            "descriptionRaw": "Voltaren Emulgel <p>Voltaren Emulgel Extra Sterk 2,32% is een ontstekingsremmende gel die wordt gebruikt voor de lokale verlichting van milde tot matige gewrichtspijn, zoals veroorzaakt door artrose, in de knie\u00ebn en vingers. Voltaren Emulgel Extra Sterk bevat een extra sterke concentratie (2,32%) diclofenac, een niet-stero\u00efdale ontstekingsremmer (NSAID). Diclofenac werkt pijnstillend en ontstekingsremmend in de bron. De pijnverlichting van Voltaren Emulgel bouwt zich geleidelijk op gedurende de eerste week van de behandeling. 1 keer aanbrengen per 12 uur op de te behandelen plek. Voltaren Emulgel Extra Sterk 2,32% nu met een nieuwe makkelijk te openen dop in 1 klik. Voltaren Emulgel 2,32% (diclofenac diethylammononium) is een geneesmiddel. Voltaren niet gebruiken gedurende het laatste trimester van de zwangerschap.</p>"
          },
          "priceHistory": {
            "lowestPrice": 25.99
          },
          "priceHistoryBe": {
            "lowestPrice": 29.99
          },
          "title": "Voltaren Emulgel extra sterk 2.32% ( roemeense verpakking ) 150g",
          "fixedTitle": "Voltaren Emulgel extra sterk 2.32% 150g",
          "indexIdentifierTimeStamp": 1744737669,
          "description": "Voltaren Emulgel extra sterk 2.32% ( roemeense verpakking ) 150g op voorraad. Voor 23:00 besteld, morgen in huis. Profiteer van gratis verzending.",
          "descriptionRaw": "Voltaren Emulgel extra sterk 2.32% ( roemeense verpakking ) 150g op voorraad. Voor 23:00 besteld, morgen in huis. Profiteer van gratis verzending.",
          "descriptionDuplicate": false,
          "descriptionToShow": "shop",
          "properties": "",
          "price": null,
          "itemId": 1147539272,
          "gtinGroupId": "286-3G6ftwpEqsKLu2V8REoGDhhEBcAQ",
          "categoryId": 9002302,
          "mainCategoryId": 286,
          "mainCategoryUrl": "gezond_mooi",
          "csvId": 1229508185928,
          "shopCount": 1,
          "paidShopCount": 1,
          "hybridShopCount": 6,
          "shopIds": [
            16034
          ],
          "images": [
            {
              "imageType": "mainImage",
              "size": {
                "height": 319,
                "width": 1199
              },
              "type": "mainImage",
              "url": "pim/5054563923912/394/{size}/c069e93d02220537c99a79d19de18ff9/Spierbalsems/Voltaren-Emulgel-extra-sterk-2.32%25-150g.jpg"
            },
            {
              "imageType": "alternativeImage1",
              "size": {
                "height": 886,
                "width": 697
              },
              "type": "alternativeImage",
              "url": "pim/5054563923912/15376/{size}/c4689e00a76307477324dd7c79b4bf47/Spierbalsems/Voltaren-Emulgel-extra-sterk-2.32%25-150g.jpg"
            },
            {
              "imageType": "alternativeImage2",
              "size": {
                "height": 999,
                "width": 999
              },
              "type": "alternativeImage",
              "url": "pim/5054563923912/15377/{size}/dae119f0149abd3e2ebf60d0dcd98fc0/Spierbalsems/Voltaren-Emulgel-extra-sterk-2.32%25-150g.jpg"
            },
            {
              "imageType": "alternativeImage3",
              "size": {
                "height": 918,
                "width": 799
              },
              "type": "alternativeImage",
              "url": "pim/5054563923912/15378/{size}/6d7c844914cbe1899323b1ddf3cf452d/Spierbalsems/Voltaren-Emulgel-extra-sterk-2.32%25-150g.jpg"
            },
            {
              "imageType": "alternativeImage4",
              "size": {
                "height": 887,
                "width": 727
              },
              "type": "alternativeImage",
              "url": "pim/5054563923912/15379/{size}/28b91702dcb32e679ea149be24aa6382/Spierbalsems/Voltaren-Emulgel-extra-sterk-2.32%25-150g.jpg"
            }
          ],
          "sizes": [],
          "columnsPerOffer": [],
          "defaultSizeAvailable": false,
          "brandId": 252185,
          "brandName": "Voltaren",
          "brandRank": null,
          "brandRelativeDemandLabel": null,
          "extras": {
            "used": false
          },
          "firstAddition": "2023-02-16 00:00:00",
          "popularity": 227,
          "popularityData": {
            "clickFactor": 4,
            "webshopsRevenuePerClick": 4.32,
            "roasPercentage": 900
          },
          "searchScore": 0,
          "searchGroup": 0,
          "searchGroupName": null,
          "enriched": null,
          "deliveryText": "Op werkdagen voor 23:00 uur besteld, morgen in huis",
          "deliveryTimeSort": 2,
          "deliveryCosts": 0,
          "facets": [
            {
              "id": 114,
              "name": "Merk",
              "isTopFacet": true,
              "isShownOnPlp": true,
              "urlName": "merk",
              "value": "Voltaren",
              "values": [
                {
                  "id": 252185,
                  "caption": "Voltaren",
                  "columnValue": "Voltaren",
                  "crawlable": true,
                  "detailValue": "Voltaren",
                  "fullId": "114_252185",
                  "sequence": 3598,
                  "urlName": null
                }
              ]
            },
            {
              "id": 115,
              "name": "Winkel",
              "isTopFacet": false,
              "isShownOnPlp": true,
              "urlName": "winkel",
              "value": "Drogist.nl",
              "values": [
                {
                  "id": 1296939,
                  "caption": "Drogist.nl",
                  "columnValue": "Drogist.nl",
                  "crawlable": true,
                  "detailValue": "Drogist.nl",
                  "fullId": "115_1296939",
                  "sequence": 214,
                  "urlName": null
                }
              ]
            },
            {
              "id": 3323,
              "name": "Doelgroep",
              "isTopFacet": true,
              "isShownOnPlp": true,
              "urlName": "doelgroep_drogisterij",
              "value": "Volwassenen",
              "values": [
                {
                  "id": 23581740,
                  "caption": "Volwassenen",
                  "columnValue": "Volwassenen",
                  "crawlable": true,
                  "detailValue": "Volwassenen",
                  "fullId": "3323_23581740",
                  "sequence": 5,
                  "urlName": null
                }
              ]
            },
            {
              "id": 4240,
              "name": "Werkzame stof",
              "isTopFacet": true,
              "isShownOnPlp": true,
              "urlName": "ws_geneesmiddel",
              "value": "Diclofenac",
              "values": [
                {
                  "id": 9016060,
                  "caption": "Diclofenac",
                  "columnValue": "Diclofenac",
                  "crawlable": true,
                  "detailValue": "Diclofenac",
                  "fullId": "4240_9016060",
                  "sequence": 18,
                  "urlName": null
                }
              ]
            },
            {
              "id": 6245,
              "name": "Inhoud",
              "isTopFacet": true,
              "isShownOnPlp": true,
              "urlName": "inhoud_ml",
              "value": "150 gr",
              "values": [
                {
                  "id": 23754875,
                  "caption": "150 gr",
                  "columnValue": "150 gr",
                  "crawlable": false,
                  "detailValue": "150 gr",
                  "fullId": "6245_23754875",
                  "sequence": 93,
                  "urlName": null
                }
              ]
            },
            {
              "id": 6414,
              "name": "Productlijn",
              "isTopFacet": false,
              "isShownOnPlp": true,
              "urlName": "pl_geneesmiddelen",
              "value": "Emulgel Extra Sterk",
              "values": [
                {
                  "id": 23754967,
                  "caption": "Emulgel Extra Sterk",
                  "columnValue": "Emulgel Extra Sterk",
                  "crawlable": true,
                  "detailValue": "Emulgel Extra Sterk",
                  "fullId": "6414_23754967",
                  "sequence": 72,
                  "urlName": null
                }
              ]
            },
            {
              "id": 6416,
              "name": "Te gebruiken bij",
              "isTopFacet": true,
              "isShownOnPlp": true,
              "urlName": "indicaties_pijn",
              "value": "Gewrichtspijn",
              "values": [
                {
                  "id": 23755164,
                  "caption": "Gewrichtspijn",
                  "columnValue": "Gewrichtspijn",
                  "crawlable": true,
                  "detailValue": "Gewrichtspijn",
                  "fullId": "6416_23755164",
                  "sequence": 1,
                  "urlName": null
                },
                {
                  "id": 23755172,
                  "caption": "Ontsteking",
                  "columnValue": "Ontsteking",
                  "crawlable": true,
                  "detailValue": "Ontsteking",
                  "fullId": "6416_23755172",
                  "sequence": 9,
                  "urlName": null
                }
              ]
            }
          ],
          "siblingCode": "16034-144238",
          "relatedSiblingDetails": null,
          "bidData": null,
          "bidApiData": {
            "cps": null
          },
          "missingSearchWords": [],
          "shopActive": true,
          "pim3puntNullId": "nl-nl-gold-5054563923912",
          "revenuePerClick": 0.48,
          "sorting": {
            "fastestDelivery": 1,
            "priceIncludingDelivery": 0,
            "priceExcludingDelivery": 0,
            "revenuePerClick": 0,
            "shopscore": 0
          },
          "allShopsLowestPrice": 25.99,
          "facetsValues": [],
          "productScoreLabel": "A",
          "eanScoreLabel": "APLUS",
          "isGoogleBestseller": true,
          "isGoogleBestsellerTop100": true,
          "productRating": null,
          "labels": [],
          "discountPercentage": null,
          "debugData": [],
          "usps": [
            {
              "type": "shopReviewScore",
              "score": 9.4,
              "amount": 85784
            },
            {
              "type": "freeDeliveryCost"
            }
          ]
        },
        {
          "id": "3uugKutJRn8LHjce7jdT9pCcGZZq",
          "type": "nonmatching",
          "productSearchId": {
            "familyIdV3": "3uugKutJRn8LHjce7jdT9pCcGZZq",
            "advertisementIdV3": "3uugKutJRn8LHjce7jdT9pCcGZZq"
          },
          "shopItemId": 0,
          "productId": "3uugKutJRn8LHjce7jdT9pCcGZZq",
          "ean": "",
          "shopInfo": {
            "id": 2513,
            "shopName": "Kruidvat.nl",
            "shopPhase": 1,
            "isActive": true,
            "isAffiliate": false,
            "hasFreeReturnCondition": false,
            "shopType": "CPC",
            "isClosedOnSunday": false,
            "isBlendedCpcWw": false,
            "isCSSShop": false,
            "allowBackOrder": true,
            "sortLower": null,
            "feedBiddingEnabled": false,
            "smartBiddingEnabled": true,
            "listedOnNl": true,
            "listedOnBe": false,
            "bvBucket": 2,
            "productCount": 10500,
            "isDisabled": false,
            "hideOnline": false,
            "includesVat": true,
            "logo": "/beslist-images/shop_images/LARGE/2513.png",
            "coolingOffPeriod": 14,
            "activeSince": "2025-04-15T05:02:32+02:00",
            "emailGeneral": "",
            "emailFinanceAdmin": "",
            "emailCustomerContact": "info@Kruidvat.nl",
            "sharesGoogleAnalyticsData": false,
            "principalClient": {
              "clientId": 18803,
              "clientName": "",
              "clientAddress": "",
              "clientZipCode": "",
              "clientCity": "",
              "clientCountry": "",
              "clientEmailITAccess": "",
              "clientEmailGeneral": "",
              "clientEmailFinanceAdmin": "",
              "clientEmailCustomerContact": "",
              "clientVatNumber": ""
            },
            "deliveryCompanies": [
              {
                "id": 4,
                "name": "DHL"
              }
            ],
            "paymentOptions": [
              {
                "id": 17,
                "name": "iDEAL"
              },
              {
                "id": 18,
                "name": "Visa"
              },
              {
                "id": 19,
                "name": "Mastercard"
              }
            ],
            "qualityMarks": [
              {
                "id": 2,
                "name": "Thuiswinkel Waarborg"
              }
            ]
          },
          "shopItem": {
            "shopId": 2513,
            "shopItemId": 0,
            "shopItemTitle": "Voltaren Emulgel Extra Sterk 2,32% (diclofenac) Gel Lees de",
            "shopItemDescription": "",
            "shopItemVersion": "5421459",
            "shopName": "Kruidvat.nl",
            "shopType": "CPC",
            "productIdentifier": "",
            "productIdV3": "3uugKutJRn8LHjce7jdT9pCcGZZq",
            "condition": "Nieuw",
            "ean": "5054563923912",
            "blockStatus": 0,
            "disabledInFeed": false,
            "url": "https://www.kruidvat.nl/voltaren-emulgel-extra-sterk-2-32-diclofenac-gel/p/5421459?utm_campaign=Sales&utm_content=Gezondheid_Zelfzorg_Voltaren&utm_source=Beslist_Overig_11111&utm_medium=COM&utm_term=5421459",
            "size": "",
            "shopReviewScore": 4.2,
            "shopReviewAmount": 2433,
            "isBlendedCpcWw": false,
            "shopPhase": 1,
            "salePrice": null,
            "regularPrice": {
              "bucket": 21,
              "price": 32.99,
              "validFrom": null,
              "validThrough": null
            },
            "bvbCode": "5421459",
            "bidLabel": null
          },
          "pim": {
            "groupId": null,
            "title": "Voltaren Emulgel Extra Sterk 2,32% - 1 x 150 gr",
            "description": "Voltaren Emulgel Voltaren Emulgel Extra Sterk 2,32% is een ontstekingsremmende gel die wordt gebruikt voor de lokale verlichting van milde tot matige gewrichtspijn, zoals veroorzaakt door artrose, in de knie\u00ebn en vingers. Voltaren Emulgel Extra Sterk bevat een extra sterke concentratie (2,32%) diclofenac, een niet-stero\u00efdale ontstekingsremmer (NSAID). Diclofenac werkt pijnstillend en ontstekingsremmend in de bron. De pijnverlichting van Voltaren Emulgel bouwt zich geleidelijk op gedurende de eerste week van de behandeling. 1 keer aanbrengen per 12 uur op de te behandelen plek. Voltaren Emulgel Extra Sterk 2,32% nu met een nieuwe makkelijk te openen dop in 1 klik. Voltaren Emulgel 2,32% (diclofenac diethylammononium) is een geneesmiddel. Voltaren niet gebruiken gedurende het laatste trimester van de zwangerschap.",
            "descriptionRaw": "Voltaren Emulgel <p>Voltaren Emulgel Extra Sterk 2,32% is een ontstekingsremmende gel die wordt gebruikt voor de lokale verlichting van milde tot matige gewrichtspijn, zoals veroorzaakt door artrose, in de knie\u00ebn en vingers. Voltaren Emulgel Extra Sterk bevat een extra sterke concentratie (2,32%) diclofenac, een niet-stero\u00efdale ontstekingsremmer (NSAID). Diclofenac werkt pijnstillend en ontstekingsremmend in de bron. De pijnverlichting van Voltaren Emulgel bouwt zich geleidelijk op gedurende de eerste week van de behandeling. 1 keer aanbrengen per 12 uur op de te behandelen plek. Voltaren Emulgel Extra Sterk 2,32% nu met een nieuwe makkelijk te openen dop in 1 klik. Voltaren Emulgel 2,32% (diclofenac diethylammononium) is een geneesmiddel. Voltaren niet gebruiken gedurende het laatste trimester van de zwangerschap.</p>"
          },
          "priceHistory": {
            "lowestPrice": 25.99
          },
          "priceHistoryBe": {
            "lowestPrice": 29.99
          },
          "title": "Voltaren Emulgel Extra Sterk 2,32% (diclofenac) Gel Lees de",
          "fixedTitle": "Voltaren Emulgel Extra Sterk 2,32% (diclofenac) Gel Lees de",
          "indexIdentifierTimeStamp": 1744737669,
          "description": "Gebruik Voltaren Emulgel Extra Sterk 2,32% (diclofenac) Gel bij spier- en gewrichtsblessures, zoals sportblessures en voor lokale verlichting van milde tot matige gewrichtspijn door artrose in je knie of vingers. Voltaren Emulgel Extra Sterk 2,32% (diclofenac) Gel verlicht je pijn, remt je ontsteking, vermindert je zwelling en versnelt het herstel bij spierpijn en gewrichtspijn. De gel werkt in de bron van je pijn en biedt pijnverlichting tot twaalf uur lang.\n\nGebruik de gel bij ontstekingen en pijn van traumatische of reumatische oorsprong en symptomatische behandeling van lokale pijn van lichte tot matige intensiteit in verband met spier- en gewrichtsletsel, bijvoorbeeld sportblessures. Breng de gel bijvoorbeeld aan op je rug, nek, schouder of knie. \n\nVoltaren Emugel Extra Sterkt 2,32% versnelt de genezing met vier dagen bij een enkelverstuiking. De gel verlicht je pijn en remt de onsteking bij Osteo Arthritis in je knie en vinger.\n\nNiet gebruiken tijdens het derde trimester van je",
          "descriptionRaw": "Gebruik Voltaren Emulgel Extra Sterk 2,32% (diclofenac) Gel bij spier- en gewrichtsblessures, zoals sportblessures en voor lokale verlichting van milde tot matige gewrichtspijn door artrose in je knie of vingers. Voltaren Emulgel Extra Sterk 2,32% (diclofenac) Gel verlicht je pijn, remt je ontsteking, vermindert je zwelling en versnelt het herstel bij spierpijn en gewrichtspijn. De gel werkt in de bron van je pijn en biedt pijnverlichting tot twaalf uur lang.\n\nGebruik de gel bij ontstekingen en pijn van traumatische of reumatische oorsprong en symptomatische behandeling van lokale pijn van lichte tot matige intensiteit in verband met spier- en gewrichtsletsel, bijvoorbeeld sportblessures. Breng de gel bijvoorbeeld aan op je rug, nek, schouder of knie. \n\nVoltaren Emugel Extra Sterkt 2,32% versnelt de genezing met vier dagen bij een enkelverstuiking. De gel verlicht je pijn en remt de onsteking bij Osteo Arthritis in je knie en vinger.\n\nNiet gebruiken tijdens het derde trimester van je",
          "descriptionDuplicate": false,
          "descriptionToShow": "shop",
          "properties": "",
          "price": null,
          "itemId": null,
          "gtinGroupId": "286-3uugKutJRn8LHjce7jdT9pCcGZZq",
          "categoryId": 9002302,
          "mainCategoryId": 286,
          "mainCategoryUrl": "gezond_mooi",
          "csvId": null,
          "shopCount": 1,
          "paidShopCount": 1,
          "hybridShopCount": 6,
          "shopIds": [
            2513
          ],
          "images": [
            {
              "imageType": "mainImage",
              "size": {
                "height": 319,
                "width": 1199
              },
              "type": "mainImage",
              "url": "pim/5054563923912/394/{size}/c069e93d02220537c99a79d19de18ff9/Spierbalsems/Voltaren-Emulgel-Extra-Sterk-2%2c32%25-(diclofenac)-Gel-Lees-de.jpg"
            },
            {
              "imageType": "alternativeImage1",
              "size": {
                "height": 886,
                "width": 697
              },
              "type": "alternativeImage",
              "url": "pim/5054563923912/15376/{size}/c4689e00a76307477324dd7c79b4bf47/Spierbalsems/Voltaren-Emulgel-Extra-Sterk-2%2c32%25-(diclofenac)-Gel-Lees-de.jpg"
            },
            {
              "imageType": "alternativeImage2",
              "size": {
                "height": 999,
                "width": 999
              },
              "type": "alternativeImage",
              "url": "pim/5054563923912/15377/{size}/dae119f0149abd3e2ebf60d0dcd98fc0/Spierbalsems/Voltaren-Emulgel-Extra-Sterk-2%2c32%25-(diclofenac)-Gel-Lees-de.jpg"
            },
            {
              "imageType": "alternativeImage3",
              "size": {
                "height": 918,
                "width": 799
              },
              "type": "alternativeImage",
              "url": "pim/5054563923912/15378/{size}/6d7c844914cbe1899323b1ddf3cf452d/Spierbalsems/Voltaren-Emulgel-Extra-Sterk-2%2c32%25-(diclofenac)-Gel-Lees-de.jpg"
            },
            {
              "imageType": "alternativeImage4",
              "size": {
                "height": 887,
                "width": 727
              },
              "type": "alternativeImage",
              "url": "pim/5054563923912/15379/{size}/28b91702dcb32e679ea149be24aa6382/Spierbalsems/Voltaren-Emulgel-Extra-Sterk-2%2c32%25-(diclofenac)-Gel-Lees-de.jpg"
            }
          ],
          "sizes": [],
          "columnsPerOffer": [],
          "defaultSizeAvailable": false,
          "brandId": 252185,
          "brandName": "Voltaren",
          "brandRank": null,
          "brandRelativeDemandLabel": null,
          "extras": {
            "used": false
          },
          "firstAddition": "2024-05-01 00:00:00",
          "popularity": 21,
          "popularityData": {
            "clickFactor": 0,
            "webshopsRevenuePerClick": null,
            "roasPercentage": null
          },
          "searchScore": 0,
          "searchGroup": 0,
          "searchGroupName": null,
          "enriched": null,
          "deliveryText": "Op werkdagen voor 20:00 uur besteld, volgende dag in huis",
          "deliveryTimeSort": 2,
          "deliveryCosts": 3.99,
          "facets": [
            {
              "id": 114,
              "name": "Merk",
              "isTopFacet": true,
              "isShownOnPlp": true,
              "urlName": "merk",
              "value": "Voltaren",
              "values": [
                {
                  "id": 252185,
                  "caption": "Voltaren",
                  "columnValue": "Voltaren",
                  "crawlable": true,
                  "detailValue": "Voltaren",
                  "fullId": "114_252185",
                  "sequence": 3598,
                  "urlName": null
                }
              ]
            },
            {
              "id": 115,
              "name": "Winkel",
              "isTopFacet": false,
              "isShownOnPlp": true,
              "urlName": "winkel",
              "value": "Kruidvat.nl",
              "values": [
                {
                  "id": 5581822,
                  "caption": "Kruidvat.nl",
                  "columnValue": "Kruidvat.nl",
                  "crawlable": true,
                  "detailValue": "Kruidvat.nl",
                  "fullId": "115_5581822",
                  "sequence": 459,
                  "urlName": null
                }
              ]
            },
            {
              "id": 3323,
              "name": "Doelgroep",
              "isTopFacet": true,
              "isShownOnPlp": true,
              "urlName": "doelgroep_drogisterij",
              "value": "Volwassenen",
              "values": [
                {
                  "id": 23581740,
                  "caption": "Volwassenen",
                  "columnValue": "Volwassenen",
                  "crawlable": true,
                  "detailValue": "Volwassenen",
                  "fullId": "3323_23581740",
                  "sequence": 5,
                  "urlName": null
                }
              ]
            },
            {
              "id": 4240,
              "name": "Werkzame stof",
              "isTopFacet": true,
              "isShownOnPlp": true,
              "urlName": "ws_geneesmiddel",
              "value": "Diclofenac",
              "values": [
                {
                  "id": 9016060,
                  "caption": "Diclofenac",
                  "columnValue": "Diclofenac",
                  "crawlable": true,
                  "detailValue": "Diclofenac",
                  "fullId": "4240_9016060",
                  "sequence": 18,
                  "urlName": null
                }
              ]
            },
            {
              "id": 4710,
              "name": "Toediening",
              "isTopFacet": true,
              "isShownOnPlp": true,
              "urlName": "t_toediening",
              "value": "Gel",
              "values": [
                {
                  "id": 9287228,
                  "caption": "Gel",
                  "columnValue": "Gel",
                  "crawlable": true,
                  "detailValue": "Gel",
                  "fullId": "4710_9287228",
                  "sequence": 10,
                  "urlName": null
                }
              ]
            },
            {
              "id": 6414,
              "name": "Productlijn",
              "isTopFacet": false,
              "isShownOnPlp": true,
              "urlName": "pl_geneesmiddelen",
              "value": "Emulgel Extra Sterk",
              "values": [
                {
                  "id": 23754967,
                  "caption": "Emulgel Extra Sterk",
                  "columnValue": "Emulgel Extra Sterk",
                  "crawlable": true,
                  "detailValue": "Emulgel Extra Sterk",
                  "fullId": "6414_23754967",
                  "sequence": 72,
                  "urlName": null
                }
              ]
            },
            {
              "id": 6416,
              "name": "Te gebruiken bij",
              "isTopFacet": true,
              "isShownOnPlp": true,
              "urlName": "indicaties_pijn",
              "value": "Gewrichtspijn",
              "values": [
                {
                  "id": 23755164,
                  "caption": "Gewrichtspijn",
                  "columnValue": "Gewrichtspijn",
                  "crawlable": true,
                  "detailValue": "Gewrichtspijn",
                  "fullId": "6416_23755164",
                  "sequence": 1,
                  "urlName": null
                },
                {
                  "id": 23755172,
                  "caption": "Ontsteking",
                  "columnValue": "Ontsteking",
                  "crawlable": true,
                  "detailValue": "Ontsteking",
                  "fullId": "6416_23755172",
                  "sequence": 9,
                  "urlName": null
                },
                {
                  "id": 23755163,
                  "caption": "Spierpijn",
                  "columnValue": "Spierpijn",
                  "crawlable": true,
                  "detailValue": "Spierpijn",
                  "fullId": "6416_23755163",
                  "sequence": 11,
                  "urlName": null
                }
              ]
            }
          ],
          "siblingCode": "",
          "relatedSiblingDetails": null,
          "bidData": null,
          "bidApiData": {
            "cps": null
          },
          "missingSearchWords": [],
          "shopActive": true,
          "pim3puntNullId": "nl-nl-gold-5054563923912",
          "revenuePerClick": 0.22,
          "sorting": {
            "fastestDelivery": 0,
            "priceIncludingDelivery": 1,
            "priceExcludingDelivery": 1,
            "revenuePerClick": 2,
            "shopscore": 2
          },
          "allShopsLowestPrice": 25.99,
          "facetsValues": [],
          "productScoreLabel": null,
          "eanScoreLabel": "APLUS",
          "isGoogleBestseller": true,
          "isGoogleBestsellerTop100": true,
          "productRating": null,
          "labels": [],
          "discountPercentage": null,
          "debugData": [],
          "usps": []
        },
        {
          "id": "2PuJM1jDyF93q1VkkFVaoEF1sBuE",
          "type": "nonmatching",
          "productSearchId": {
            "familyIdV3": "2PuJM1jDyF93q1VkkFVaoEF1sBuE",
            "advertisementIdV3": "2PuJM1jDyF93q1VkkFVaoEF1sBuE"
          },
          "shopItemId": 0,
          "productId": "2PuJM1jDyF93q1VkkFVaoEF1sBuE",
          "ean": "",
          "shopInfo": {
            "id": 597860,
            "shopName": "Medischevakhandel.nl",
            "shopPhase": 1,
            "isActive": true,
            "isAffiliate": false,
            "hasFreeReturnCondition": false,
            "shopType": "CPC",
            "isClosedOnSunday": false,
            "isBlendedCpcWw": false,
            "isCSSShop": true,
            "allowBackOrder": true,
            "sortLower": null,
            "feedBiddingEnabled": false,
            "smartBiddingEnabled": true,
            "listedOnNl": true,
            "listedOnBe": false,
            "bvBucket": 7,
            "productCount": 2700,
            "isDisabled": false,
            "hideOnline": false,
            "includesVat": true,
            "logo": "/beslist-images/shop_images/LARGE/597860.png",
            "coolingOffPeriod": 14,
            "activeSince": "2025-04-15T05:02:31+02:00",
            "emailGeneral": "",
            "emailFinanceAdmin": "",
            "emailCustomerContact": "info@Medischevakhandel.nl",
            "sharesGoogleAnalyticsData": false,
            "principalClient": {
              "clientId": 20878,
              "clientName": "",
              "clientAddress": "",
              "clientZipCode": "",
              "clientCity": "",
              "clientCountry": "",
              "clientEmailITAccess": "",
              "clientEmailGeneral": "",
              "clientEmailFinanceAdmin": "",
              "clientEmailCustomerContact": "",
              "clientVatNumber": ""
            },
            "deliveryCompanies": [
              {
                "id": 1,
                "name": "PostNL"
              }
            ],
            "paymentOptions": [
              {
                "id": 17,
                "name": "iDEAL"
              },
              {
                "id": 9,
                "name": "PayPal"
              },
              {
                "id": 18,
                "name": "Visa"
              },
              {
                "id": 19,
                "name": "Mastercard"
              },
              {
                "id": 35,
                "name": "Maestro"
              },
              {
                "id": 24,
                "name": "Bancontact"
              }
            ],
            "qualityMarks": []
          },
          "shopItem": {
            "shopId": 597860,
            "shopItemId": 0,
            "shopItemTitle": "Voltaren Emulgel extra sterk 2.32% 150 gram",
            "shopItemDescription": "",
            "shopItemVersion": "122801696",
            "shopName": "Medischevakhandel.nl",
            "shopType": "CPC",
            "productIdentifier": "",
            "productIdV3": "2PuJM1jDyF93q1VkkFVaoEF1sBuE",
            "condition": "Nieuw",
            "ean": "5054563923912",
            "blockStatus": 0,
            "disabledInFeed": false,
            "url": "https://www.medischevakhandel.nl/nl/voltaren-emulgel-extra-sterk-2-32-150-gram?utm_source=beslist&utm_medium=cpc&utm_campaign=beslist",
            "size": "",
            "shopReviewScore": 4.6,
            "shopReviewAmount": 12,
            "isBlendedCpcWw": false,
            "shopPhase": 1,
            "salePrice": null,
            "regularPrice": {
              "bucket": 34,
              "price": 38.59,
              "validFrom": null,
              "validThrough": null
            },
            "bvbCode": "122801696",
            "bidLabel": null
          },
          "pim": {
            "groupId": null,
            "title": "Voltaren Emulgel Extra Sterk 2,32% - 1 x 150 gr",
            "description": "Voltaren Emulgel Voltaren Emulgel Extra Sterk 2,32% is een ontstekingsremmende gel die wordt gebruikt voor de lokale verlichting van milde tot matige gewrichtspijn, zoals veroorzaakt door artrose, in de knie\u00ebn en vingers. Voltaren Emulgel Extra Sterk bevat een extra sterke concentratie (2,32%) diclofenac, een niet-stero\u00efdale ontstekingsremmer (NSAID). Diclofenac werkt pijnstillend en ontstekingsremmend in de bron. De pijnverlichting van Voltaren Emulgel bouwt zich geleidelijk op gedurende de eerste week van de behandeling. 1 keer aanbrengen per 12 uur op de te behandelen plek. Voltaren Emulgel Extra Sterk 2,32% nu met een nieuwe makkelijk te openen dop in 1 klik. Voltaren Emulgel 2,32% (diclofenac diethylammononium) is een geneesmiddel. Voltaren niet gebruiken gedurende het laatste trimester van de zwangerschap.",
            "descriptionRaw": "Voltaren Emulgel <p>Voltaren Emulgel Extra Sterk 2,32% is een ontstekingsremmende gel die wordt gebruikt voor de lokale verlichting van milde tot matige gewrichtspijn, zoals veroorzaakt door artrose, in de knie\u00ebn en vingers. Voltaren Emulgel Extra Sterk bevat een extra sterke concentratie (2,32%) diclofenac, een niet-stero\u00efdale ontstekingsremmer (NSAID). Diclofenac werkt pijnstillend en ontstekingsremmend in de bron. De pijnverlichting van Voltaren Emulgel bouwt zich geleidelijk op gedurende de eerste week van de behandeling. 1 keer aanbrengen per 12 uur op de te behandelen plek. Voltaren Emulgel Extra Sterk 2,32% nu met een nieuwe makkelijk te openen dop in 1 klik. Voltaren Emulgel 2,32% (diclofenac diethylammononium) is een geneesmiddel. Voltaren niet gebruiken gedurende het laatste trimester van de zwangerschap.</p>"
          },
          "priceHistory": {
            "lowestPrice": 25.99
          },
          "priceHistoryBe": {
            "lowestPrice": 29.99
          },
          "title": "Voltaren Emulgel extra sterk 2.32% 150 gram",
          "fixedTitle": "Voltaren Emulgel extra sterk 2.32% 150 gram",
          "indexIdentifierTimeStamp": 1744737669,
          "description": "TE GEBRUIKEN BIJ  Voltaren Emulgel Extra Sterk wordt gebruikt bij volwassenen voor de lokale verlichting van milde tot matige gewrichtspijn, veroorzaakt door verergering van artrose van de knie of vingers.  NIET TE GEBRUIKEN BIJ  U bent allergisch voor \u00e9\u00e9n van de stoffen in dit geneesmiddel. Tijdens het derde trimester van uw zwangerschap.  DOSERING Breng de gel om de 12 uur (bij voorkeur \u2019s morgens en \u2019s avonds) aan op de pijnlijke plek REGISTRATIEGEGEVENSZI-nummer: 16997549EAN code: 5054563923912RVG nummer: 117734GENEESMIDDELLet op: dit is een geneesmiddel uitsluitend verkrijgbaar via Apotheek en Drogist (UAD). We adviseren je dit product alleen te gebruiken als je goed ge\u00efnformeerd bent.VERDERE INFORMATIEVoor meer aanvullende informatie verwijzen we je naar:  Geneesmiddeleninformatiebank van medicijnautoriteit CBG Apotheek.nl Thuisarts.nl",
          "descriptionRaw": "TE GEBRUIKEN BIJ  Voltaren Emulgel Extra Sterk wordt gebruikt bij volwassenen voor de lokale verlichting van milde tot matige gewrichtspijn, veroorzaakt door verergering van artrose van de knie of vingers.  NIET TE GEBRUIKEN BIJ  U bent allergisch voor \u00e9\u00e9n van de stoffen in dit geneesmiddel. Tijdens het derde trimester van uw zwangerschap.  DOSERING Breng de gel om de 12 uur (bij voorkeur \u2019s morgens en \u2019s avonds) aan op de pijnlijke plek REGISTRATIEGEGEVENSZI-nummer: 16997549EAN code: 5054563923912RVG nummer: 117734GENEESMIDDELLet op: dit is een geneesmiddel uitsluitend verkrijgbaar via Apotheek en Drogist (UAD). We adviseren je dit product alleen te gebruiken als je goed ge\u00efnformeerd bent.VERDERE INFORMATIEVoor meer aanvullende informatie verwijzen we je naar:  Geneesmiddeleninformatiebank van medicijnautoriteit CBG Apotheek.nl Thuisarts.nl",
          "descriptionDuplicate": false,
          "descriptionToShow": "pim",
          "properties": "",
          "price": null,
          "itemId": null,
          "gtinGroupId": "286-2PuJM1jDyF93q1VkkFVaoEF1sBuE",
          "categoryId": 9002302,
          "mainCategoryId": 286,
          "mainCategoryUrl": "gezond_mooi",
          "csvId": null,
          "shopCount": 1,
          "paidShopCount": 1,
          "hybridShopCount": 6,
          "shopIds": [
            597860
          ],
          "images": [
            {
              "imageType": "mainImage",
              "size": {
                "height": 319,
                "width": 1199
              },
              "type": "mainImage",
              "url": "pim/5054563923912/394/{size}/c069e93d02220537c99a79d19de18ff9/Spierbalsems/Voltaren-Emulgel-extra-sterk-2.32%25-150-gram.jpg"
            },
            {
              "imageType": "alternativeImage1",
              "size": {
                "height": 886,
                "width": 697
              },
              "type": "alternativeImage",
              "url": "pim/5054563923912/15376/{size}/c4689e00a76307477324dd7c79b4bf47/Spierbalsems/Voltaren-Emulgel-extra-sterk-2.32%25-150-gram.jpg"
            },
            {
              "imageType": "alternativeImage2",
              "size": {
                "height": 999,
                "width": 999
              },
              "type": "alternativeImage",
              "url": "pim/5054563923912/15377/{size}/dae119f0149abd3e2ebf60d0dcd98fc0/Spierbalsems/Voltaren-Emulgel-extra-sterk-2.32%25-150-gram.jpg"
            },
            {
              "imageType": "alternativeImage3",
              "size": {
                "height": 918,
                "width": 799
              },
              "type": "alternativeImage",
              "url": "pim/5054563923912/15378/{size}/6d7c844914cbe1899323b1ddf3cf452d/Spierbalsems/Voltaren-Emulgel-extra-sterk-2.32%25-150-gram.jpg"
            },
            {
              "imageType": "alternativeImage4",
              "size": {
                "height": 887,
                "width": 727
              },
              "type": "alternativeImage",
              "url": "pim/5054563923912/15379/{size}/28b91702dcb32e679ea149be24aa6382/Spierbalsems/Voltaren-Emulgel-extra-sterk-2.32%25-150-gram.jpg"
            }
          ],
          "sizes": [],
          "columnsPerOffer": [],
          "defaultSizeAvailable": false,
          "brandId": 252185,
          "brandName": "Voltaren",
          "brandRank": null,
          "brandRelativeDemandLabel": null,
          "extras": {
            "used": false
          },
          "firstAddition": "2024-05-01 00:00:00",
          "popularity": 221,
          "popularityData": {
            "clickFactor": 8,
            "webshopsRevenuePerClick": null,
            "roasPercentage": null
          },
          "searchScore": 0,
          "searchGroup": 0,
          "searchGroupName": null,
          "enriched": null,
          "deliveryText": "1 - 3 werkdagen",
          "deliveryTimeSort": 3,
          "deliveryCosts": 7.99,
          "facets": [
            {
              "id": 114,
              "name": "Merk",
              "isTopFacet": true,
              "isShownOnPlp": true,
              "urlName": "merk",
              "value": "Voltaren",
              "values": [
                {
                  "id": 252185,
                  "caption": "Voltaren",
                  "columnValue": "Voltaren",
                  "crawlable": true,
                  "detailValue": "Voltaren",
                  "fullId": "114_252185",
                  "sequence": 3598,
                  "urlName": null
                }
              ]
            },
            {
              "id": 115,
              "name": "Winkel",
              "isTopFacet": false,
              "isShownOnPlp": true,
              "urlName": "winkel",
              "value": "Medischevakhandel.nl",
              "values": [
                {
                  "id": 19249542,
                  "caption": "Medischevakhandel.nl",
                  "columnValue": "Medischevakhandel.nl",
                  "crawlable": true,
                  "detailValue": "Medischevakhandel.nl",
                  "fullId": "115_19249542",
                  "sequence": 511,
                  "urlName": null
                }
              ]
            },
            {
              "id": 4710,
              "name": "Toediening",
              "isTopFacet": true,
              "isShownOnPlp": true,
              "urlName": "t_toediening",
              "value": "Gel",
              "values": [
                {
                  "id": 9287228,
                  "caption": "Gel",
                  "columnValue": "Gel",
                  "crawlable": true,
                  "detailValue": "Gel",
                  "fullId": "4710_9287228",
                  "sequence": 10,
                  "urlName": null
                }
              ]
            },
            {
              "id": 6245,
              "name": "Inhoud",
              "isTopFacet": true,
              "isShownOnPlp": true,
              "urlName": "inhoud_ml",
              "value": "150 gr",
              "values": [
                {
                  "id": 23754875,
                  "caption": "150 gr",
                  "columnValue": "150 gr",
                  "crawlable": false,
                  "detailValue": "150 gr",
                  "fullId": "6245_23754875",
                  "sequence": 93,
                  "urlName": null
                }
              ]
            }
          ],
          "siblingCode": "",
          "relatedSiblingDetails": null,
          "bidData": null,
          "bidApiData": {
            "cps": null
          },
          "missingSearchWords": [],
          "shopActive": true,
          "pim3puntNullId": "nl-nl-gold-5054563923912",
          "revenuePerClick": 0.25,
          "sorting": {
            "fastestDelivery": 2,
            "priceIncludingDelivery": 2,
            "priceExcludingDelivery": 2,
            "revenuePerClick": 1,
            "shopscore": 1
          },
          "allShopsLowestPrice": 25.99,
          "facetsValues": [],
          "productScoreLabel": "C",
          "eanScoreLabel": "APLUS",
          "isGoogleBestseller": true,
          "isGoogleBestsellerTop100": true,
          "productRating": null,
          "labels": [],
          "discountPercentage": null,
          "debugData": [],
          "usps": []
        }
      ],
      "facetSet": [],
      "facetSetSelected": [],
      "shopInfoSet": []
    }
  ]
}